[{
  "_id": {
    "$oid": "6556280b8b4d270a9b21aa1a"
  },
  "username": "shivdeep",
  "serviceProviderName": "FedEx",
  "serviceProviderRating": "2",
  "feedback": "IT is nice",
  "orderID": "1233",
  "dateOfService": "2023-11-15",
  "recommendService": "false",
  "__v": 0
},
{
  "_id": {
    "$oid": "655628628b4d270a9b21aa1c"
  },
  "username": "shivdeep",
  "serviceProviderName": "USPS",
  "serviceProviderRating": "1",
  "feedback": "sdf",
  "orderID": "12113",
  "dateOfService": "2023-11-16",
  "recommendService": "false",
  "__v": 0
},
{
  "_id": {
    "$oid": "65562a443ded94a8acddcc8c"
  },
  "username": "abhi",
  "serviceProviderName": "FedEx",
  "serviceProviderRating": "3",
  "feedback": "dddd",
  "orderID": "1235822",
  "dateOfService": "2023-11-17",
  "recommendService": "false",
  "__v": 0
},
{
  "_id": {
    "$oid": "65562c9d3ded94a8acddcc8e"
  },
  "username": "shivdeep",
  "serviceProviderName": "USPS",
  "serviceProviderRating": "3",
  "feedback": "wedfg",
  "orderID": "12113",
  "dateOfService": "2023-11-16",
  "recommendService": "false",
  "__v": 0
},
{
  "_id": {
    "$oid": "65563c293ded94a8acddcc90"
  },
  "username": "shivdeep",
  "serviceProviderName": "UPS",
  "serviceProviderRating": "1",
  "feedback": "sdfff",
  "orderID": "12113",
  "dateOfService": "2023-11-16",
  "recommendService": "false",
  "__v": 0
},
{
  "_id": {
    "$oid": "65563e913ded94a8acddcc92"
  },
  "username": "sbisurkar@hawk.iit.edu",
  "serviceProviderName": "USPS",
  "serviceProviderRating": "2",
  "feedback": "asdf",
  "orderID": "12113",
  "dateOfService": "2023-11-17",
  "recommendService": "false",
  "__v": 0
},
{
  "_id": {
    "$oid": "655649633ded94a8acddcc94"
  },
  "username": "shivdeep",
  "serviceProviderName": "FedEx",
  "serviceProviderRating": "2",
  "feedback": "bhkfjgk,h",
  "orderID": "hbjn.",
  "dateOfService": "2023-11-16",
  "recommendService": "false",
  "__v": 0
},
{
  "_id": {
    "$oid": "65564c413ded94a8acddcc96"
  },
  "username": "Amit",
  "serviceProviderName": "UPS",
  "serviceProviderRating": "3",
  "feedback": "niranjan is good",
  "orderID": "12345656",
  "dateOfService": "2023-11-15",
  "recommendService": "true",
  "__v": 0
},
{
  "_id": {
    "$oid": "65564c893ded94a8acddcc98"
  },
  "username": "shivdeep",
  "serviceProviderName": "UPS",
  "serviceProviderRating": "2",
  "feedback": "asdsd",
  "orderID": "12113",
  "dateOfService": "2023-11-16",
  "recommendService": "true",
  "__v": 0
},
{
  "_id": {
    "$oid": "65564ca83ded94a8acddcc9a"
  },
  "username": "abcd",
  "serviceProviderName": "UPS",
  "serviceProviderRating": "3",
  "feedback": "good",
  "orderID": "12113",
  "dateOfService": "2023-11-16",
  "recommendService": "false",
  "__v": 0
},
{
  "_id": {
    "$oid": "6556962ba3b55fa1135c5d13"
  },
  "username": "Ram",
  "serviceProviderName": "UPS",
  "serviceProviderRating": "1",
  "feedback": "asdfghjkl;';lkjhgfdsdfghjkl;'",
  "orderID": "123",
  "dateOfService": "2023-11-14",
  "recommendService": "true",
  "__v": 0
},
{
  "_id": {
    "$oid": "6563f10df3bb7cb999f3d44b"
  },
  "username": "Atharva",
  "serviceProviderName": "UPS",
  "serviceProviderRating": "4",
  "feedback": "It is very good product",
  "orderID": "1235",
  "dateOfService": "2023-11-27",
  "recommendService": "true",
  "__v": 0
},
{
  "_id": {
    "$oid": "656a015b228299130c0694b7"
  },
  "username": "deep",
  "serviceProviderName": "USPS",
  "serviceProviderRating": "2",
  "feedback": "cnnkc",
  "orderID": "1235",
  "dateOfService": "2023-12-02",
  "recommendService": "true",
  "__v": 0
},
{
  "_id": {
    "$oid": "656a1758228299130c0694b9"
  },
  "username": "shivdeep",
  "serviceProviderName": "USPS",
  "serviceProviderRating": "2",
  "feedback": "s dkdnn",
  "orderID": "1235",
  "dateOfService": "2023-12-02",
  "recommendService": "true",
  "__v": 0
},
{
  "_id": {
    "$oid": "656a2ac5228299130c0694cb"
  },
  "username": "Niranjan",
  "serviceProviderName": "UPS",
  "serviceProviderRating": "2",
  "feedback": "goddd",
  "orderID": "1235",
  "dateOfService": "2023-12-02",
  "recommendService": "false",
  "__v": 0
},
{
  "_id": {
    "$oid": "656a2f3c228299130c0694cd"
  },
  "username": "shivdeep",
  "serviceProviderName": "UPS",
  "serviceProviderRating": "2",
  "feedback": "yes it is",
  "orderID": "1235",
  "dateOfService": "2023-12-02",
  "recommendService": "true",
  "__v": 0
},
{
  "_id": {
    "$oid": "656a361223ccecf744da1333"
  },
  "username": "deep",
  "serviceProviderName": "UPS",
  "serviceProviderRating": "1",
  "feedback": "good but didn't like",
  "orderID": "1235",
  "dateOfService": "2023-12-27",
  "recommendService": "true",
  "__v": 0
}]